pytracking/__init__.py
pytracking/django.py
pytracking/html.py
pytracking/tracking.py
pytracking/webhook.py
pytracking2-0.4.6.dist-info/LICENSE
pytracking2-0.4.6.dist-info/METADATA
pytracking2-0.4.6.dist-info/WHEEL
pytracking2-0.4.6.dist-info/top_level.txt
pytracking2-0.4.6.dist-info/RECORD
