Metadata-Version: 2.1
Name: pytracking2
Version: 0.4.6
Summary: Email open and click tracking
Home-page: https://github.com/xelixdev/pytracking
Author: Mikuláš Poul
Author-email: mikulas.poul@xelix.com
License: New BSD
Keywords: email open click tracking
Platform: UNKNOWN
Classifier: Development Status :: 5 - Production/Stable
Classifier: Intended Audience :: Developers
Classifier: Topic :: Communications :: Email
Classifier: Topic :: Software Development :: Libraries :: Python Modules
Classifier: License :: OSI Approved :: BSD License
Classifier: Programming Language :: Python
Classifier: Programming Language :: Python :: 3
Classifier: Programming Language :: Python :: 3.8
Classifier: Programming Language :: Python :: 3.9
Classifier: Programming Language :: Python :: 3.10
Classifier: Programming Language :: Python :: 3.11
Classifier: Programming Language :: Python :: 3.12
Requires-Python: >=3.8
License-File: LICENSE
Provides-Extra: all
Requires-Dist: tox ; extra == 'all'
Requires-Dist: pytest ; extra == 'all'
Requires-Dist: pytest-django ; extra == 'all'
Requires-Dist: requests (>=2.10.0) ; extra == 'all'
Requires-Dist: lxml (>=4.4.0) ; extra == 'all'
Requires-Dist: cryptography (>=2.0.0) ; extra == 'all'
Requires-Dist: django-ipware (>=2.0.0) ; extra == 'all'
Requires-Dist: django (>=4.2) ; extra == 'all'
Provides-Extra: crypto
Requires-Dist: cryptography (>=2.0.0) ; extra == 'crypto'
Provides-Extra: django
Requires-Dist: django-ipware (>=2.0.0) ; extra == 'django'
Requires-Dist: django (>=4.2) ; extra == 'django'
Provides-Extra: html
Requires-Dist: lxml (>=4.4.0) ; extra == 'html'
Provides-Extra: test
Requires-Dist: tox ; extra == 'test'
Requires-Dist: pytest ; extra == 'test'
Requires-Dist: pytest-django ; extra == 'test'
Provides-Extra: webhook
Requires-Dist: requests (>=2.10.0) ; extra == 'webhook'
